<annotation>
	<folder>五峰旗</folder>
	<filename>217.jpg</filename>
	<path>/home/yungaisun/dlib/reportPic/yilan/五峰旗/217.jpg</path>
	<source>
		<database>Unknown</database>
	</source>
	<size>
		<width>500</width>
		<height>334</height>
		<depth>3</depth>
	</size>
	<segmented>0</segmented>
	<object>
		<name>wufengciWaterfall</name>
		<pose>Unspecified</pose>
		<truncated>0</truncated>
		<difficult>0</difficult>
		<bndbox>
			<xmin>328</xmin>
			<ymin>9</ymin>
			<xmax>441</xmax>
			<ymax>258</ymax>
		</bndbox>
	</object>
</annotation>
