<annotation>
	<folder>五峰旗</folder>
	<filename>235.jpg</filename>
	<path>/home/yungaisun/dlib/reportPic/yilan/五峰旗/235.jpg</path>
	<source>
		<database>Unknown</database>
	</source>
	<size>
		<width>333</width>
		<height>499</height>
		<depth>3</depth>
	</size>
	<segmented>0</segmented>
	<object>
		<name>wufengciWaterfall</name>
		<pose>Unspecified</pose>
		<truncated>0</truncated>
		<difficult>0</difficult>
		<bndbox>
			<xmin>47</xmin>
			<ymin>109</ymin>
			<xmax>139</xmax>
			<ymax>323</ymax>
		</bndbox>
	</object>
</annotation>
