<annotation>
	<folder>turtleIslandAll</folder>
	<filename>196.jpg</filename>
	<path>/home/yungaisun/dlib/yilan/turtleIslandAll/196.jpg</path>
	<source>
		<database>Unknown</database>
	</source>
	<size>
		<width>499</width>
		<height>335</height>
		<depth>3</depth>
	</size>
	<segmented>0</segmented>
	<object>
		<name>turtleIsland</name>
		<pose>Unspecified</pose>
		<truncated>0</truncated>
		<difficult>0</difficult>
		<bndbox>
			<xmin>218</xmin>
			<ymin>55</ymin>
			<xmax>448</xmax>
			<ymax>115</ymax>
		</bndbox>
	</object>
</annotation>
